CHANGES.rst
MANIFEST.in
Makefile
Makefile.release
README.rst
setup.py
version.txt
src/arstecnica.sqlalchemy.async.egg-info/PKG-INFO
src/arstecnica.sqlalchemy.async.egg-info/SOURCES.txt
src/arstecnica.sqlalchemy.async.egg-info/dependency_links.txt
src/arstecnica.sqlalchemy.async.egg-info/namespace_packages.txt
src/arstecnica.sqlalchemy.async.egg-info/requires.txt
src/arstecnica.sqlalchemy.async.egg-info/top_level.txt
src/arstecnica/sqlalchemy/async/__init__.py
src/arstecnica/sqlalchemy/async/tests/__init__.py
src/arstecnica/sqlalchemy/async/tests/_test_connect_35.py
src/arstecnica/sqlalchemy/async/tests/conftest.py
src/arstecnica/sqlalchemy/async/tests/test_connect.py