Metadata-Version: 1.1
Name: arstecnica.sqlalchemy.async
Version: 0.4
Summary: Asyncio middleware for SQLAlchemy
Home-page: https://gitlab.com/arstecnica/arstecnica.sqlalchemy.async
Author: Lele Gaifax
Author-email: lele@metapensiero.it
License: GPLv3+
Keywords: asyncio sqlalchemy
Platform: UNKNOWN
Classifier: Programming Language :: Python
Classifier: Programming Language :: Python :: 3
Classifier: Programming Language :: Python :: 3.4
Classifier: Programming Language :: Python :: 3.5
Classifier: Intended Audience :: Developers
Classifier: License :: OSI Approved :: GNU General Public License v3 or later (GPLv3+)
Classifier: Topic :: Database
